steamtags/__init__.py
steamtags/api.py
steamtags/tests/__init__.py
steamtags/tests/test_steamtags.py
steamtags-0.1.2.dist-info/LICENSE
steamtags-0.1.2.dist-info/METADATA
steamtags-0.1.2.dist-info/WHEEL
steamtags-0.1.2.dist-info/top_level.txt
steamtags-0.1.2.dist-info/RECORD
