Metadata-Version: 2.1
Name: steamtags
Version: 0.1.2
Summary: Steam Tags on PyPI
Home-page: https://github.com/woctezuma/match-steam-tags
Author: Wok
Author-email: wok@tuta.io
License: UNKNOWN
Download-URL: https://github.com/woctezuma/match-steam-tags/archive/0.1.2.tar.gz
Keywords: steam,steamtags,tags,api
Platform: UNKNOWN
Classifier: Development Status :: 3 - Alpha
Classifier: Topic :: Games/Entertainment
Classifier: Programming Language :: Python :: 3
Classifier: License :: OSI Approved :: MIT License
Classifier: Operating System :: OS Independent
Requires-Python: >=3
Requires-Dist: steamspypi
